Metadata-Version: 2.1
Name: xorencryption
Version: 0.1.6
Summary: little Python library for encrypt and decrypt using XOR operation.
Home-page: https://github.com/AlvifSandana/xorencryption
Author: Alvif Sandana Mahardika
Author-email: alvifsandana@gmail.com
License: MIT
Download-URL: https://github.com/AlvifSandana/xorencryption/
Keywords: XOR,LEARN,CRYPTOGRAPHY
Platform: UNKNOWN
Classifier: Development Status :: 4 - Beta
Classifier: Intended Audience :: Developers
Classifier: Topic :: Software Development :: Build Tools
Classifier: License :: OSI Approved :: MIT License
Classifier: Programming Language :: Python :: 3
Requires-Python: >=3.7
